[{"symbol": "SZ002747", "name": "\u57c3\u65af\u987f", "close": 24.29, "percent": 10.01, "volume": 17006469, "amount": 396247816, "type_name": ["\u65e5\u6da8\u5e45\u504f\u79bb\u503c\u8fbe7%\u7684\u8bc1\u5238"]}, {"symbol": "SH605111", "name": "\u65b0\u6d01\u80fd", "close": 119.79, "percent": 10, "volume": 2498487, "amount": 299293758, "type_name": ["\u65e5\u6da8\u5e45\u504f\u79bb\u503c\u8fbe7%\u7684\u8bc1\u5238"]}, {"symbol": "SZ300446", "name": "ST\u4e50\u51ef", "close": 11.3, "percent": 19.96, "volume": 22683747, "amount": 252701395, "type_name": ["\u8fde\u7eed3\u4e2a\u4ea4\u6613\u65e5\u5185\u6536\u76d8\u4ef7\u683c\u6da8\u5e45\u8f83\u57fa\u51c6\u6307\u6570\u504f\u79bb\u503c\u7d2f\u8ba1\u8fbe\u523030%\u7684\u8bc1\u5238"]}, {"symbol": "SZ300350", "name": "\u534e\u9e4f\u98de", "close": 7.33, "percent": 19.97, "volume": 54141103, "amount": 383009506, "type_name": ["\u6709\u4ef7\u683c\u6da8\u8dcc\u5e45\u9650\u5236\u7684\u65e5\u6536\u76d8\u4ef7\u683c\u6da8\u5e45\u8fbe\u523015%\u7684\u8bc1\u5238"]}, {"symbol": "SH601865", "name": "\u798f\u83b1\u7279", "close": 37.14, "percent": 7.65, "volume": 21535687, "amount": 765328470, "type_name": ["\u65e5\u6da8\u5e45\u504f\u79bb\u503c\u8fbe7%\u7684\u8bc1\u5238"]}, {"symbol": "SZ002759", "name": "\u5929\u9645\u80a1\u4efd", "close": 15.87, "percent": 9.98, "volume": 28303668, "amount": 424523048, "type_name": ["\u65e5\u6da8\u5e45\u504f\u79bb\u503c\u8fbe7%\u7684\u8bc1\u5238"]}, {"symbol": "SZ300314", "name": "\u6234\u7ef4\u533b\u7597", "close": 24.78, "percent": 20, "volume": 23276640, "amount": 548622326, "type_name": ["\u6709\u4ef7\u683c\u6da8\u8dcc\u5e45\u9650\u5236\u7684\u65e5\u6536\u76d8\u4ef7\u683c\u6da8\u5e45\u8fbe\u523015%\u7684\u8bc1\u5238"]}, {"symbol": "SZ300589", "name": "\u6c5f\u9f99\u8239\u8247", "close": 36.8, "percent": 19.99, "volume": 33643143, "amount": 1215550785, "type_name": ["\u6709\u4ef7\u683c\u6da8\u8dcc\u5e45\u9650\u5236\u7684\u65e5\u6536\u76d8\u4ef7\u683c\u6da8\u5e45\u8fbe\u523015%\u7684\u8bc1\u5238"]}, {"symbol": "SH605058", "name": "\u6fb3\u5f18\u7535\u5b50", "close": 27.37, "percent": -6.65, "volume": 11067439, "amount": 305792510, "type_name": ["\u65e5\u6362\u624b\u7387\u8fbe20%\u7684\u8bc1\u5238"]}, {"symbol": "SZ003013", "name": "\u5730\u94c1\u8bbe\u8ba1", "close": 24.35, "percent": 4.06, "volume": 22700213, "amount": 538506518, "type_name": ["\u65e5\u632f\u5e45\u503c\u8fbe15%\u7684\u8bc1\u5238", "\u65e5\u6362\u624b\u7387\u8fbe20%\u7684\u8bc1\u5238"]}, {"symbol": "SZ300490", "name": "\u534e\u81ea\u79d1\u6280", "close": 14.89, "percent": 13.93, "volume": 66623615, "amount": 1032817336, "type_name": ["\u8fde\u7eed3\u4e2a\u4ea4\u6613\u65e5\u5185\u6536\u76d8\u4ef7\u683c\u6da8\u5e45\u8f83\u57fa\u51c6\u6307\u6570\u504f\u79bb\u503c\u7d2f\u8ba1\u8fbe\u523030%\u7684\u8bc1\u5238"]}, {"symbol": "SZ002531", "name": "\u5929\u987a\u98ce\u80fd", "close": 7.36, "percent": -9.47, "volume": 139738329, "amount": 1043351243, "type_name": ["\u65e5\u8dcc\u5e45\u504f\u79bb\u503c\u8fbe7%\u7684\u8bc1\u5238"]}, {"symbol": "SH600161", "name": "\u5929\u575b\u751f\u7269", "close": 37.26, "percent": -8.72, "volume": 39440650, "amount": 1490209194, "type_name": ["\u65e5\u8dcc\u5e45\u504f\u79bb\u503c\u8fbe7%\u7684\u8bc1\u5238"]}, {"symbol": "SH601187", "name": "\u53a6\u95e8\u94f6\u884c", "close": 9.41, "percent": 40.24, "volume": 134661461, "amount": 1225382298, "type_name": ["\u65e0\u4ef7\u683c\u6da8\u8dcc\u5e45\u9650\u5236\u7684\u8bc1\u5238", "\u5f53\u65e5\u65e0\u4ef7\u683c\u6da8\u8dcc\u5e45\u9650\u5236\u7684A\u80a1\uff0c\u51fa\u73b0\u5f02\u5e38\u6ce2\u52a8\u505c\u724c", "\u65b0\u80a1\u9996\u65e5\u4ea4\u6613\u4fe1\u606f"]}, {"symbol": "SZ002497", "name": "\u96c5\u5316\u96c6\u56e2", "close": 13.02, "percent": 9.97, "volume": 124555106, "amount": 1591091437, "type_name": ["\u65e5\u6da8\u5e45\u504f\u79bb\u503c\u8fbe7%\u7684\u8bc1\u5238"]}, {"symbol": "SZ300898", "name": "\u718a\u732b\u4e73\u54c1", "close": 74.1, "percent": -4.74, "volume": 15617546, "amount": 1162624360, "type_name": ["\u6709\u4ef7\u683c\u6da8\u8dcc\u5e45\u9650\u5236\u7684\u65e5\u6362\u624b\u7387\u8fbe\u523030%\u7684\u8bc1\u5238"]}, {"symbol": "SZ002196", "name": "\u65b9\u6b63\u7535\u673a", "close": 6.32, "percent": -7.87, "volume": 51619819, "amount": 328511362, "type_name": ["\u65e5\u8dcc\u5e45\u504f\u79bb\u503c\u8fbe7%\u7684\u8bc1\u5238"]}, {"symbol": "SZ002518", "name": "\u79d1\u58eb\u8fbe", "close": 14, "percent": -9.97, "volume": 19090317, "amount": 273160674, "type_name": ["\u65e5\u8dcc\u5e45\u504f\u79bb\u503c\u8fbe7%\u7684\u8bc1\u5238"]}, {"symbol": "SZ300880", "name": "\u8fe6\u5357\u667a\u80fd", "close": 55, "percent": -3.73, "volume": 15444677, "amount": 891928603, "type_name": ["\u6709\u4ef7\u683c\u6da8\u8dcc\u5e45\u9650\u5236\u7684\u65e5\u6362\u624b\u7387\u8fbe\u523030%\u7684\u8bc1\u5238"]}, {"symbol": "SZ002114", "name": "\u7f57\u5e73\u950c\u7535", "close": 6.6, "percent": -6.38, "volume": 30327545, "amount": 209428552, "type_name": ["\u65e5\u632f\u5e45\u503c\u8fbe15%\u7684\u8bc1\u5238"]}, {"symbol": "SZ003010", "name": "\u82e5\u7fbd\u81e3", "close": 46.68, "percent": 1.54, "volume": 6507057, "amount": 296175323, "type_name": ["\u65e5\u6362\u624b\u7387\u8fbe20%\u7684\u8bc1\u5238"]}, {"symbol": "SZ300819", "name": "\u805a\u6770\u5fae\u7ea4", "close": 52.18, "percent": 8.21, "volume": 16304272, "amount": 820110482, "type_name": ["\u6709\u4ef7\u683c\u6da8\u8dcc\u5e45\u9650\u5236\u7684\u65e5\u6362\u624b\u7387\u8fbe\u523030%\u7684\u8bc1\u5238"]}, {"symbol": "SZ000056", "name": "\u7687\u5ead\u56fd\u9645", "close": 3.57, "percent": -6.79, "volume": 24010290, "amount": 85174037, "type_name": ["\u65e5\u8dcc\u5e45\u504f\u79bb\u503c\u8fbe7%\u7684\u8bc1\u5238"]}, {"symbol": "SH605338", "name": "\u5df4\u6bd4\u98df\u54c1", "close": 46, "percent": -3.22, "volume": 18190725, "amount": 839709200, "type_name": ["\u65e5\u6362\u624b\u7387\u8fbe20%\u7684\u8bc1\u5238"]}, {"symbol": "SZ000816", "name": "\u667a\u6167\u519c\u4e1a", "close": 1.65, "percent": 10, "volume": 2682437, "amount": 4426021, "type_name": ["\u65e5\u6da8\u5e45\u504f\u79bb\u503c\u8fbe7%\u7684\u8bc1\u5238"]}, {"symbol": "SH603283", "name": "\u8d5b\u817e\u80a1\u4efd", "close": 48.83, "percent": -10.01, "volume": 1157100, "amount": 57023675, "type_name": ["\u65e5\u8dcc\u5e45\u504f\u79bb\u503c\u8fbe7%\u7684\u8bc1\u5238"]}, {"symbol": "SH603212", "name": "\u8d5b\u4f0d\u6280\u672f", "close": 33.48, "percent": 8.49, "volume": 4694230, "amount": 153070539, "type_name": ["\u65e5\u6da8\u5e45\u504f\u79bb\u503c\u8fbe7%\u7684\u8bc1\u5238"]}, {"symbol": "SZ300578", "name": "\u4f1a\u7545\u901a\u8baf", "close": 41.04, "percent": 20, "volume": 14398639, "amount": 577506024, "type_name": ["\u6709\u4ef7\u683c\u6da8\u8dcc\u5e45\u9650\u5236\u7684\u65e5\u6536\u76d8\u4ef7\u683c\u6da8\u5e45\u8fbe\u523015%\u7684\u8bc1\u5238"]}, {"symbol": "SZ002664", "name": "\u957f\u9e70\u4fe1\u8d28", "close": 13.99, "percent": -8.8, "volume": 25468208, "amount": 354593429, "type_name": ["\u65e5\u8dcc\u5e45\u504f\u79bb\u503c\u8fbe7%\u7684\u8bc1\u5238", "\u8fde\u7eed\u4e09\u4e2a\u4ea4\u6613\u65e5\u5185,\u8dcc\u5e45\u504f\u79bb\u503c\u7d2f\u8ba1\u8fbe20%\u7684\u8bc1\u5238"]}, {"symbol": "SH605136", "name": "\u4e3d\u4eba\u4e3d\u5986", "close": 43.06, "percent": -7.12, "volume": 18881782, "amount": 820304051, "type_name": ["\u65e5\u6362\u624b\u7387\u8fbe20%\u7684\u8bc1\u5238"]}, {"symbol": "SZ300431", "name": "\u66b4\u98ce\u9000", "close": 0.31, "percent": 6.9, "volume": 11177128, "amount": 3421084, "type_name": [""]}, {"symbol": "SZ002240", "name": "\u76db\u65b0\u9502\u80fd", "close": 13.16, "percent": 10.03, "volume": 36956137, "amount": 476749428, "type_name": ["\u65e5\u6da8\u5e45\u504f\u79bb\u503c\u8fbe7%\u7684\u8bc1\u5238"]}, {"symbol": "SZ300345", "name": "\u534e\u6c11\u80a1\u4efd", "close": 6.68, "percent": -20, "volume": 44624803, "amount": 317155857, "type_name": ["\u6709\u4ef7\u683c\u6da8\u8dcc\u5e45\u9650\u5236\u7684\u65e5\u6536\u76d8\u4ef7\u683c\u8dcc\u5e45\u8fbe\u5230-15%\u7684\u8bc1\u5238"]}, {"symbol": "SH600460", "name": "\u58eb\u5170\u5fae", "close": 15.1, "percent": -7.81, "volume": 36517222, "amount": 562053294, "type_name": ["\u65e5\u8dcc\u5e45\u504f\u79bb\u503c\u8fbe7%\u7684\u8bc1\u5238"]}, {"symbol": "SH688386", "name": "\u6cdb\u4e9a\u5fae\u900f", "close": 49.75, "percent": 8.18, "volume": 5832139, "amount": 282451955, "type_name": ["\u6709\u4ef7\u683c\u6da8\u8dcc\u5e45\u9650\u5236\u7684\u65e5\u6362\u624b\u7387\u8fbe\u523030%\u7684\u8bc1\u5238"]}, {"symbol": "SZ002524", "name": "\u5149\u6b63\u773c\u79d1", "close": 12.64, "percent": 10.01, "volume": 35766427, "amount": 444473311, "type_name": ["\u65e5\u6da8\u5e45\u504f\u79bb\u503c\u8fbe7%\u7684\u8bc1\u5238"]}, {"symbol": "SZ003016", "name": "\u6b23\u8d3a\u80a1\u4efd", "close": 12.96, "percent": 0.08, "volume": 47352022, "amount": 631784287, "type_name": ["\u65e5\u6362\u624b\u7387\u8fbe20%\u7684\u8bc1\u5238"]}, {"symbol": "SZ300062", "name": "\u4e2d\u80fd\u7535\u6c14", "close": 20.05, "percent": 9.32, "volume": 100110833, "amount": 1901705553, "type_name": ["\u6709\u4ef7\u683c\u6da8\u8dcc\u5e45\u9650\u5236\u7684\u65e5\u6362\u624b\u7387\u8fbe\u523030%\u7684\u8bc1\u5238"]}, {"symbol": "SH601333", "name": "\u5e7f\u6df1\u94c1\u8def", "close": 2.34, "percent": -0.43, "volume": 16788103, "amount": 39266800, "type_name": ["\u5f53\u65e5\u878d\u8d44\u4e70\u5165\u6570\u91cf\u8fbe\u5230\u5f53\u65e5\u8be5\u8bc1\u5238\u603b\u4ea4\u6613\u91cf\u768450\uff05\u4ee5\u4e0a"]}, {"symbol": "SZ300899", "name": "\u4e0a\u6d77\u51ef\u946b", "close": 84.98, "percent": 19.99, "volume": 9748347, "amount": 748482263, "type_name": ["\u6709\u4ef7\u683c\u6da8\u8dcc\u5e45\u9650\u5236\u7684\u65e5\u4ef7\u683c\u632f\u5e45\u8fbe\u523030%\u7684\u8bc1\u5238", "\u6709\u4ef7\u683c\u6da8\u8dcc\u5e45\u9650\u5236\u7684\u65e5\u6362\u624b\u7387\u8fbe\u523030%\u7684\u8bc1\u5238", "\u6709\u4ef7\u683c\u6da8\u8dcc\u5e45\u9650\u5236\u7684\u65e5\u6536\u76d8\u4ef7\u683c\u6da8\u5e45\u8fbe\u523015%\u7684\u8bc1\u5238"]}, {"symbol": "SZ002247", "name": "*ST\u805a\u529b", "close": 1.72, "percent": -4.97, "volume": 2480900, "amount": 4267148, "type_name": ["\u8fde\u7eed\u4e09\u4e2a\u4ea4\u6613\u65e5\u5185\uff0c\u8dcc\u5e45\u504f\u79bb\u503c\u7d2f\u8ba1\u8fbe\u523012%\u7684ST\u8bc1\u5238\u3001*ST\u8bc1\u5238\u548c\u672a\u5b8c\u6210\u80a1\u6539\u8bc1\u5238"]}, {"symbol": "SZ000661", "name": "\u957f\u6625\u9ad8\u65b0", "close": 381.17, "percent": 10, "volume": 10895596, "amount": 4026867950, "type_name": ["\u65e5\u6da8\u5e45\u504f\u79bb\u503c\u8fbe7%\u7684\u8bc1\u5238"]}, {"symbol": "SZ002242", "name": "\u4e5d\u9633\u80a1\u4efd", "close": 40.28, "percent": -9.99, "volume": 6440160, "amount": 261058187, "type_name": ["\u65e5\u8dcc\u5e45\u504f\u79bb\u503c\u8fbe7%\u7684\u8bc1\u5238"]}]