{"id": 86091563, "status": "pending", "cube_id": 1387899, "prev_bebalancing_id": 86076591, "category": "user_rebalancing", "exe_strategy": "intraday_all", "created_at": 1607584297101, "updated_at": 1607584297101, "cash": 18.13, "error_code": "20842", "cash_value": 2.24545633, "error_message": "\u7531\u4e8e\u73b0\u5728\u4f11\u5e02\uff0c\u7ec4\u5408\u5904\u4e8e\u300c\u5f85\u6210\u4ea4\u300d\u72b6\u6001\uff0c\u8bf7\u8010\u5fc3\u7b49\u5f85\u3002", "error_status": "\u5f85\u6210\u4ea4", "holdings": [{"stock_id": 1002022, "weight": 26.18, "segment_name": "\u6709\u8272\u91d1\u5c5e", "segment_id": 7682376, "stock_name": "\u5929\u9f50\u9502\u4e1a", "stock_symbol": "SZ002466", "segment_color": "#6b8a6b", "proactive": false, "volume": 0.02086831}, {"stock_id": 1001498, "weight": 30.69, "segment_name": "\u91c7\u6398", "segment_id": 8589734, "stock_name": "\u6cb3\u94a2\u8d44\u6e90", "stock_symbol": "SZ000923", "segment_color": "#5a5b6a", "proactive": false, "volume": 0.02593641}, {"stock_id": 1002096, "weight": 25.0, "segment_name": "\u5efa\u7b51\u88c5\u9970", "segment_id": 8435659, "stock_name": "\u9e3f\u8def\u94a2\u6784", "stock_symbol": "SZ002541", "segment_color": "#9da55d", "proactive": false, "volume": 0.01435713}], "rebalancing_histories": [], "comment": "@\u4ea4\u6613\u91cf\u5316\u6d3e \u8c03\u6574\u4e86 2 \u53ea\u80a1\u7968\uff1a\n\u5356\u51fa\u5965\u7279\u4f73\uff1a25.44% \u2192 0.00%\n\u4e70\u5165\u9e3f\u8def\u94a2\u6784\uff1a0.00% \u2192 25.00%", "diff": 0.0, "new_buy_count": 0}